{
	"$schema": "https://schemas.wp.org/trunk/block.json",
	"apiVersion": 2,
	"name": "bca/template-builder",
	"version": "0.1.0",
	"title": "Template Builder",
	"category": "widgets",
	"icon": "columns",
	"description": "Select template for posts.",
	"attributes": {
		"layout":{
			"type":"string",
			"default":"list"
		},
		"postSettings":{
			"type":"object",
			"default":{
				"categorySettings":{
					"show":true
				},
				"excerptSettings":{
					"show":true
				},
                "readMoreSettings":{
					"show":true
				},
				"metaSettings":{
					"author":{
						"show":true,
						"showIcon":false
					},
					"date":{
						"show":true
					}
				},
				"titleSettings":{
					"fontSize":"22px",
					"title":""
				},
				"thumbnailSettings":{
					"show":true,
					"alignment":"left",
					"size":"thumbnail"
				}
			}
		},
		"posts":{
			"type":"array",
			"default":[]
		},
		"query":{
			"type":"object",
			"default":{
				"_embed": true,
				"offset":0,
				"order":"desc",
				"orderby":"date",
				"per_page":4,
				"types":"post",
				"categories":[],
				"tags":[]
			}
		},
        "queryId":{
			"type":"string",
			"default":""
		},
		"template":{
			"type":"string",
			"default":"1"
		},
		"columns":{
			"type":"number",
			"default":3
		},
		"gridGap":{
			"type":"number",
			"default":15
		},
		"textAlignment":{
			"type":"string",
			"default":"left"
		}
	},
	"providesContext": {
		"bca-template-builder/query": "query",
		"bca-template-builder/postSettings": "postSettings"	
    },
	"supports": {
		"anchor":true,
		"align": true,
		"className":true,
		"color": {
			"background": true,
			"link": true,
			"text": true
		},
		"html": false,
		"spacing": {
			"margin": true,
			"padding": true,
			"blockGap": true
		}

	},
	"textdomain": "bca-template-builder",
	"editorScript": "file:./index.js",
	"editorStyle": "file:./index.css",
	"style": "file:./style-index.css"
}
